{
  "values": {
    "signal_steps": {
      "Float": 0.072
    },
    "e3": {
      "Float": 0.0
    },
    "fractal_grid_scale": {
      "Float": 0.597
    },
    "ss255": {
      "Bool": false
    },
    "64qx0": {
      "Bool": false
    },
    "fractal_color_scale": {
      "Float": 0.445
    },
    "e4": {
      "Float": 0.0
    },
    "wave_scale": {
      "Float": 0.096999995
    },
    "my3p0": {
      "Bool": false
    },
    "fractal_count": {
      "Float": 0.275
    },
    "wave_freq": {
      "Float": 0.085
    },
    "afaxn": {
      "Bool": false
    },
    "mask_falloff": {
      "Float": 0.742
    },
    "66zue": {
      "Bool": false
    },
    "wave_y": {
      "Float": 0.044999998
    },
    "signal_mix": {
      "Float": 1.0
    },
    "distort_mix": {
      "Float": 0.047
    },
    "fractal_scale": {
      "Float": 0.145
    },
    "fractal_grid_mix": {
      "Float": 0.0
    },
    "fractal_mix": {
      "Float": 0.0
    }
  }
}